 {
  "subjectName": "Anatomy",
  "lectures": [
    {
        "title": "1. Basics of Psychiatry.mp4",
        "streamingUrl": "https://stream4.nextpulse.workers.dev/watch/6645/1.+Basics+of+Psychiatry.mp4?hash=AgADzR"
    },
    {
        "title": "2. Schizophrenia other Psychotic Disorders.mp4",
        "streamingUrl": "https://stream4.nextpulse.workers.dev/watch/6646/2.+Schizophrenia+other+Psychotic+Disorders.mp4?hash=AgADzB"
    },
    {
        "title": "3. Mood DIsorder.mp4",
        "streamingUrl": "https://stream4.nextpulse.workers.dev/watch/6647/1.+Mood+DIsorder.mp4?hash=AgAD1R"
    },
    {
        "title": "4. Neurotic Stress Related Somatoform Disorders.mp4",
        "streamingUrl": "https://stream4.nextpulse.workers.dev/watch/6648/1.+Neurotic+Stress+Related+Somatoform+Disorders.mp4?hash=AgAD0R"
    },
    {
        "title": "5. Trauma and Stressor Related Disorders.mp4",
        "streamingUrl": "https://stream4.nextpulse.workers.dev/watch/6649/2.+Trauma+and+Stressor+Related+Disorders.mp4?hash=AgADyh"
    },
    {
        "title": "6.Dissocaitive_Disorders_Conversion_Disorder_Somatic_Symptoms_an.mp4",
        "streamingUrl": "https://stream4.nextpulse.workers.dev/watch/6650/3_Dissocaitive_Disorders_Conversion_Disorder_Somatic_Symptom.mp4?hash=AgADyx"
    },
    {
        "title": "7.Substance Use Addictive Disorders.mp4",
        "streamingUrl": "https://stream4.nextpulse.workers.dev/watch/6651/1.+Substance+Use+Addictive+Disorders.mp4?hash=AgAD2x"
    },
    {
        "title": "8.Child Psychiatry.mp4",
        "streamingUrl": "https://stream4.nextpulse.workers.dev/watch/6652/1.+Child+Psychiatry.mp4?hash=AgAD2R"
    },
    {
        "title": "9.Organic Mental Disorders.mp4",
        "streamingUrl": "https://stream4.nextpulse.workers.dev/watch/6653/1.+Organic+Mental+Disorders.mp4?hash=AgAD2B"
    },
    {
        "title": "10. Sleep Disorder.mp4",
        "streamingUrl": "https://stream4.nextpulse.workers.dev/watch/6654/1.+Sleep+Disorder.mp4?hash=AgADzx"
    },
    {
        "title": "11. Sexual Disorder.mp4",
        "streamingUrl": "https://stream4.nextpulse.workers.dev/watch/6655/1.+Sexual+Disorder.mp4?hash=AgADzh"
    },
    {
        "title": "12. Eating Disorders.mp4",
        "streamingUrl": "https://stream4.nextpulse.workers.dev/watch/6656/1.+Eating+Disorders.mp4?hash=AgAD0B"
    },
    {
        "title": "13. Personality Disorders.mp4",
        "streamingUrl": "https://stream4.nextpulse.workers.dev/watch/6657/1.+Personality+Disorders.mp4?hash=AgAD1B"
    },
    {
        "title": "14. Forensic Psychiatry.mp4",
        "streamingUrl": "https://stream4.nextpulse.workers.dev/watch/6658/1.+Forensic+Psychiatry.mp4?hash=AgAD0h"
    },
    {
        "title": "15. Psychology.mp4",
        "streamingUrl": "https://stream4.nextpulse.workers.dev/watch/6659/1.+Psychology.mp4?hash=AgAD1x"
    },
    {
        "title": "16. Electro Convulsive Therapy(Miscellaneous Topics).mp4",
        "streamingUrl": "https://stream4.nextpulse.workers.dev/watch/6660/1.+Electro+Convulsive+Therapy%28Miscellaneous+Topics%29.mp4?hash=AgAD0x"
    }
]
